lakkavokka/__init__.py
lakkavokka/contours.py
lakkavokka/global_mercator.py
lakkavokka/load.py
lakkavokka-0.1.0.data/scripts/lakkavokka
lakkavokka-0.1.0.dist-info/LICENSE
lakkavokka-0.1.0.dist-info/METADATA
lakkavokka-0.1.0.dist-info/WHEEL
lakkavokka-0.1.0.dist-info/top_level.txt
lakkavokka-0.1.0.dist-info/RECORD
