Metadata-Version: 2.1
Name: lakkavokka
Version: 0.1.0
Summary: Command-line JOSM plugin for digitizing indexed colors images
Home-page: https://github.com/Aneurosm/lakkavokka
Author: Miroff
Author-email: mr.miroff@gmail.com
License: MIT
Platform: UNKNOWN
Classifier: Development Status :: 4 - Beta
Classifier: Environment :: Plugins
Classifier: Environment :: Console
Classifier: Intended Audience :: Science/Research
Classifier: Intended Audience :: End Users/Desktop
Classifier: License :: OSI Approved :: MIT License
Classifier: Operating System :: POSIX :: Linux
Classifier: Programming Language :: Python :: 3.8
Classifier: Topic :: Scientific/Engineering :: GIS
Requires-Python: >=3.8
License-File: LICENSE
Requires-Dist: shapely
Requires-Dist: opencv-python
Requires-Dist: scipy
Requires-Dist: pyproj
Requires-Dist: numpy
Requires-Dist: beautifulsoup4
